echosms/__init__.py
echosms/benchmarkdata.py
echosms/dcmmodel.py
echosms/dwbamodel.py
echosms/dwbautils.py
echosms/esmodel.py
echosms/hpmodel.py
echosms/jechetaldata.py
echosms/kamodel.py
echosms/krmdata.py
echosms/krmmodel.py
echosms/mssmodel.py
echosms/psmsmodel.py
echosms/ptdwbamodel.py
echosms/referencemodels.py
echosms/scattermodelbase.py
echosms/shape_conversions.py
echosms/utils.py
echosms/utils_datastore.py
echosms/resources/DWBA_shapes.toml
echosms/resources/KRM_shapes.toml
echosms/resources/NOAA_KRM_ts_Bocaccio.csv
echosms/resources/NOAA_KRM_ts_Cod.csv
echosms/resources/NOAA_KRM_ts_Sardine.csv
echosms/resources/NOAA_KRM_ts_SkipjackTuna_46.54cm.csv
echosms/resources/target definitions.toml
echosms/resources/BenchMark_Data/Benchmark_Angle_TS.csv
echosms/resources/BenchMark_Data/Benchmark_Frequency_TS.csv
echosms/resources/Jechetal_allmodels/Figure_01_Gas-sphere.csv
echosms/resources/Jechetal_allmodels/Figure_01_PressRel-sphere.csv
echosms/resources/Jechetal_allmodels/Figure_01_Rigid-sphere.csv
echosms/resources/Jechetal_allmodels/Figure_01_WeakScatt-sphere.csv
echosms/resources/Jechetal_allmodels/Figure_02_Gas-shellsphere.csv
echosms/resources/Jechetal_allmodels/Figure_02_PressRel-shellsphere.csv
echosms/resources/Jechetal_allmodels/Figure_02_WeakScatt-shellsphere.csv
echosms/resources/Jechetal_allmodels/Figure_03-04_Gas-Pspheroid.csv
echosms/resources/Jechetal_allmodels/Figure_03-04_PressRel-Pspheroid.csv
echosms/resources/Jechetal_allmodels/Figure_03-04_Rigid-Pspheroid.csv
echosms/resources/Jechetal_allmodels/Figure_03-04_WeakScatt-Pspheroid.csv
echosms/resources/Jechetal_allmodels/Figure_05_Gas-Pspheroid_angle-038kHz.csv
echosms/resources/Jechetal_allmodels/Figure_05_PressRel-Pspheroid_angle-038kHz.csv
echosms/resources/Jechetal_allmodels/Figure_05_Rigid-Pspheroid_angle-038kHz.csv
echosms/resources/Jechetal_allmodels/Figure_05_WeakScatt-Pspheroid_angle-038kHz.csv
echosms/resources/Jechetal_allmodels/Figure_06_Gas-Cylinder.csv
echosms-0.17.0.dist-info/METADATA
echosms-0.17.0.dist-info/WHEEL
echosms-0.17.0.dist-info/entry_points.txt
echosms-0.17.0.dist-info/licenses/LICENSE
echosms-0.17.0.dist-info/RECORD
