Metadata-Version: 2.4
Name: echosms
Version: 0.17.0
Summary: Acoustic backscattering models used in aquatic ecosystem research
Project-URL: Homepage, https://github.com/ices-tools-dev/echoSMs
Project-URL: Issues, https://github.com/ices-tools-dev/echoSMs/issues
Project-URL: Documentation, https://ices-tools-dev.github.io/echoSMs
Project-URL: Repository, https://github.com/ices-tools-dev/echoSMs
Project-URL: Discussions, https://github.com/ices-tools-dev/echoSMs/discussions
Author: Mike Jech, Gavin Macaulay
License: MIT License
License-File: LICENSE
Keywords: acoustic,backscatter,model
Classifier: Development Status :: 3 - Alpha
Classifier: Intended Audience :: Science/Research
Classifier: License :: OSI Approved :: MIT License
Classifier: Operating System :: OS Independent
Classifier: Programming Language :: Python :: 3
Classifier: Programming Language :: Python :: 3.10
Classifier: Programming Language :: Python :: 3.11
Classifier: Programming Language :: Python :: 3.12
Classifier: Programming Language :: Python :: 3.13
Classifier: Programming Language :: Python :: 3.14
Classifier: Topic :: Scientific/Engineering
Classifier: Topic :: Scientific/Engineering :: Oceanography
Classifier: Topic :: Scientific/Engineering :: Physics
Requires-Python: >=3.10
Requires-Dist: backports-strenum>=1.3.1; python_version < '3.11'
Requires-Dist: mapbox-earcut
Requires-Dist: mapply
Requires-Dist: matplotlib
Requires-Dist: numpy
Requires-Dist: pandas
Requires-Dist: scipy
Requires-Dist: shapely
Requires-Dist: spheroidalwavefunctions
Requires-Dist: tomli>=1.1.0; python_version < '3.11'
Requires-Dist: tqdm
Requires-Dist: trimesh
Requires-Dist: xarray
Provides-Extra: dev
Requires-Dist: jsonschema-rs; extra == 'dev'
Requires-Dist: matplotlib; extra == 'dev'
Requires-Dist: mkdocs-material; extra == 'dev'
Requires-Dist: mkdocstrings[python]; extra == 'dev'
Requires-Dist: orjson; extra == 'dev'
Requires-Dist: pytest; extra == 'dev'
Requires-Dist: rich; extra == 'dev'
Requires-Dist: rtoml; extra == 'dev'
Requires-Dist: twine; extra == 'dev'
Provides-Extra: viewer
Requires-Dist: requests; extra == 'viewer'
Requires-Dist: rtoml; extra == 'viewer'
Requires-Dist: tomli; (python_version < '3.11') and extra == 'viewer'
